{
  "original_name": "原始模型",
  "pruned_name": "剪枝后模型",
  "total_params": {
    "original": 7248023552,
    "pruned": 5798420480,
    "reduced": 1449603072,
    "reduction_ratio": 0.19999977395216942
  },
  "layer_params": {
    "original": 6979584000,
    "pruned": 5529980928,
    "reduced": 1449603072,
    "reduction_ratio": 0.2076919014084507
  },
  "layers": [
    {
      "layer_idx": 0,
      "total": {
        "original": 218112000,
        "pruned": 215506944,
        "reduced": 2605056,
        "reduction_ratio": 0.011943661971830987
      },
      "attention": {
        "original": 41943040,
        "pruned": 41943040,
        "reduced": 0,
        "reduction_ratio": 0.0
      },
      "mlp": {
        "original": 176160768,
        "pruned": 173555712,
        "reduced": 2605056,
        "reduction_ratio": 0.014787946428571428,
        "intermediate_size": {
          "original": 14336,
          "pruned": 14124
        }
      },
      "is_zero_layer": false
    },
    {
      "layer_idx": 1,
      "total": {
        "original": 218112000,
        "pruned": 209252352,
        "reduced": 8859648,
        "reduction_ratio": 0.04061971830985916
      },
      "attention": {
        "original": 41943040,
        "pruned": 41943040,
        "reduced": 0,
        "reduction_ratio": 0.0
      },
      "mlp": {
        "original": 176160768,
        "pruned": 167301120,
        "reduced": 8859648,
        "reduction_ratio": 0.05029296875,
        "intermediate_size": {
          "original": 14336,
          "pruned": 13615
        }
      },
      "is_zero_layer": false
    },
    {
      "layer_idx": 2,
      "total": {
        "original": 218112000,
        "pruned": 44285952,
        "reduced": 173826048,
        "reduction_ratio": 0.7969577464788732
      },
      "attention": {
        "original": 41943040,
        "pruned": 41943040,
        "reduced": 0,
        "reduction_ratio": 0.0
      },
      "mlp": {
        "original": 176160768,
        "pruned": 2334720,
        "reduced": 173826048,
        "reduction_ratio": 0.9867466517857143,
        "intermediate_size": {
          "original": 14336,
          "pruned": 190
        }
      },
      "is_zero_layer": false
    },
    {
      "layer_idx": 3,
      "total": {
        "original": 218112000,
        "pruned": 46718976,
        "reduced": 171393024,
        "reduction_ratio": 0.7858028169014084
      },
      "attention": {
        "original": 41943040,
        "pruned": 41943040,
        "reduced": 0,
        "reduction_ratio": 0.0
      },
      "mlp": {
        "original": 176160768,
        "pruned": 4767744,
        "reduced": 171393024,
        "reduction_ratio": 0.9729352678571429,
        "intermediate_size": {
          "original": 14336,
          "pruned": 388
        }
      },
      "is_zero_layer": false
    },
    {
      "layer_idx": 4,
      "total": {
        "original": 218112000,
        "pruned": 53465088,
        "reduced": 164646912,
        "reduction_ratio": 0.7548732394366198
      },
      "attention": {
        "original": 41943040,
        "pruned": 41943040,
        "reduced": 0,
        "reduction_ratio": 0.0
      },
      "mlp": {
        "original": 176160768,
        "pruned": 11513856,
        "reduced": 164646912,
        "reduction_ratio": 0.9346400669642857,
        "intermediate_size": {
          "original": 14336,
          "pruned": 937
        }
      },
      "is_zero_layer": false
    },
    {
      "layer_idx": 5,
      "total": {
        "original": 218112000,
        "pruned": 65003520,
        "reduced": 153108480,
        "reduction_ratio": 0.7019718309859155
      },
      "attention": {
        "original": 41943040,
        "pruned": 41943040,
        "reduced": 0,
        "reduction_ratio": 0.0
      },
      "mlp": {
        "original": 176160768,
        "pruned": 23052288,
        "reduced": 153108480,
        "reduction_ratio": 0.869140625,
        "intermediate_size": {
          "original": 14336,
          "pruned": 1876
        }
      },
      "is_zero_layer": false
    },
    {
      "layer_idx": 6,
      "total": {
        "original": 218112000,
        "pruned": 86962176,
        "reduced": 131149824,
        "reduction_ratio": 0.6012957746478873
      },
      "attention": {
        "original": 41943040,
        "pruned": 41943040,
        "reduced": 0,
        "reduction_ratio": 0.0
      },
      "mlp": {
        "original": 176160768,
        "pruned": 45010944,
        "reduced": 131149824,
        "reduction_ratio": 0.7444893973214286,
        "intermediate_size": {
          "original": 14336,
          "pruned": 3663
        }
      },
      "is_zero_layer": false
    },
    {
      "layer_idx": 7,
      "total": {
        "original": 218112000,
        "pruned": 105885696,
        "reduced": 112226304,
        "reduction_ratio": 0.5145352112676056
      },
      "attention": {
        "original": 41943040,
        "pruned": 41943040,
        "reduced": 0,
        "reduction_ratio": 0.0
      },
      "mlp": {
        "original": 176160768,
        "pruned": 63934464,
        "reduced": 112226304,
        "reduction_ratio": 0.6370675223214286,
        "intermediate_size": {
          "original": 14336,
          "pruned": 5203
        }
      },
      "is_zero_layer": false
    },
    {
      "layer_idx": 8,
      "total": {
        "original": 218112000,
        "pruned": 116244480,
        "reduced": 101867520,
        "reduction_ratio": 0.46704225352112677
      },
      "attention": {
        "original": 41943040,
        "pruned": 41943040,
        "reduced": 0,
        "reduction_ratio": 0.0
      },
      "mlp": {
        "original": 176160768,
        "pruned": 74293248,
        "reduced": 101867520,
        "reduction_ratio": 0.5782645089285714,
        "intermediate_size": {
          "original": 14336,
          "pruned": 6046
        }
      },
      "is_zero_layer": false
    },
    {
      "layer_idx": 9,
      "total": {
        "original": 218112000,
        "pruned": 137760768,
        "reduced": 80351232,
        "reduction_ratio": 0.3683943661971831
      },
      "attention": {
        "original": 41943040,
        "pruned": 41943040,
        "reduced": 0,
        "reduction_ratio": 0.0
      },
      "mlp": {
        "original": 176160768,
        "pruned": 95809536,
        "reduced": 80351232,
        "reduction_ratio": 0.4561244419642857,
        "intermediate_size": {
          "original": 14336,
          "pruned": 7797
        }
      },
      "is_zero_layer": false
    },
    {
      "layer_idx": 10,
      "total": {
        "original": 218112000,
        "pruned": 152530944,
        "reduced": 65581056,
        "reduction_ratio": 0.3006760563380282
      },
      "attention": {
        "original": 41943040,
        "pruned": 41943040,
        "reduced": 0,
        "reduction_ratio": 0.0
      },
      "mlp": {
        "original": 176160768,
        "pruned": 110579712,
        "reduced": 65581056,
        "reduction_ratio": 0.37227957589285715,
        "intermediate_size": {
          "original": 14336,
          "pruned": 8999
        }
      },
      "is_zero_layer": false
    },
    {
      "layer_idx": 11,
      "total": {
        "original": 218112000,
        "pruned": 160751616,
        "reduced": 57360384,
        "reduction_ratio": 0.26298591549295774
      },
      "attention": {
        "original": 41943040,
        "pruned": 41943040,
        "reduced": 0,
        "reduction_ratio": 0.0
      },
      "mlp": {
        "original": 176160768,
        "pruned": 118800384,
        "reduced": 57360384,
        "reduction_ratio": 0.3256138392857143,
        "intermediate_size": {
          "original": 14336,
          "pruned": 9668
        }
      },
      "is_zero_layer": false
    },
    {
      "layer_idx": 12,
      "total": {
        "original": 218112000,
        "pruned": 172093440,
        "reduced": 46018560,
        "reduction_ratio": 0.21098591549295775
      },
      "attention": {
        "original": 41943040,
        "pruned": 41943040,
        "reduced": 0,
        "reduction_ratio": 0.0
      },
      "mlp": {
        "original": 176160768,
        "pruned": 130142208,
        "reduced": 46018560,
        "reduction_ratio": 0.26123046875,
        "intermediate_size": {
          "original": 14336,
          "pruned": 10591
        }
      },
      "is_zero_layer": false
    },
    {
      "layer_idx": 13,
      "total": {
        "original": 218112000,
        "pruned": 184688640,
        "reduced": 33423360,
        "reduction_ratio": 0.1532394366197183
      },
      "attention": {
        "original": 41943040,
        "pruned": 41943040,
        "reduced": 0,
        "reduction_ratio": 0.0
      },
      "mlp": {
        "original": 176160768,
        "pruned": 142737408,
        "reduced": 33423360,
        "reduction_ratio": 0.18973214285714285,
        "intermediate_size": {
          "original": 14336,
          "pruned": 11616
        }
      },
      "is_zero_layer": false
    },
    {
      "layer_idx": 14,
      "total": {
        "original": 218112000,
        "pruned": 192774144,
        "reduced": 25337856,
        "reduction_ratio": 0.11616901408450704
      },
      "attention": {
        "original": 41943040,
        "pruned": 41943040,
        "reduced": 0,
        "reduction_ratio": 0.0
      },
      "mlp": {
        "original": 176160768,
        "pruned": 150822912,
        "reduced": 25337856,
        "reduction_ratio": 0.14383370535714285,
        "intermediate_size": {
          "original": 14336,
          "pruned": 12274
        }
      },
      "is_zero_layer": false
    },
    {
      "layer_idx": 15,
      "total": {
        "original": 218112000,
        "pruned": 216281088,
        "reduced": 1830912,
        "reduction_ratio": 0.008394366197183098
      },
      "attention": {
        "original": 41943040,
        "pruned": 41943040,
        "reduced": 0,
        "reduction_ratio": 0.0
      },
      "mlp": {
        "original": 176160768,
        "pruned": 174329856,
        "reduced": 1830912,
        "reduction_ratio": 0.010393415178571428,
        "intermediate_size": {
          "original": 14336,
          "pruned": 14187
        }
      },
      "is_zero_layer": false
    },
    {
      "layer_idx": 16,
      "total": {
        "original": 218112000,
        "pruned": 210137088,
        "reduced": 7974912,
        "reduction_ratio": 0.03656338028169014
      },
      "attention": {
        "original": 41943040,
        "pruned": 41943040,
        "reduced": 0,
        "reduction_ratio": 0.0
      },
      "mlp": {
        "original": 176160768,
        "pruned": 168185856,
        "reduced": 7974912,
        "reduction_ratio": 0.04527064732142857,
        "intermediate_size": {
          "original": 14336,
          "pruned": 13687
        }
      },
      "is_zero_layer": false
    },
    {
      "layer_idx": 17,
      "total": {
        "original": 218112000,
        "pruned": 213590016,
        "reduced": 4521984,
        "reduction_ratio": 0.02073239436619718
      },
      "attention": {
        "original": 41943040,
        "pruned": 41943040,
        "reduced": 0,
        "reduction_ratio": 0.0
      },
      "mlp": {
        "original": 176160768,
        "pruned": 171638784,
        "reduced": 4521984,
        "reduction_ratio": 0.025669642857142856,
        "intermediate_size": {
          "original": 14336,
          "pruned": 13968
        }
      },
      "is_zero_layer": false
    },
    {
      "layer_idx": 18,
      "total": {
        "original": 218112000,
        "pruned": 214130688,
        "reduced": 3981312,
        "reduction_ratio": 0.018253521126760562
      },
      "attention": {
        "original": 41943040,
        "pruned": 41943040,
        "reduced": 0,
        "reduction_ratio": 0.0
      },
      "mlp": {
        "original": 176160768,
        "pruned": 172179456,
        "reduced": 3981312,
        "reduction_ratio": 0.022600446428571428,
        "intermediate_size": {
          "original": 14336,
          "pruned": 14012
        }
      },
      "is_zero_layer": false
    },
    {
      "layer_idx": 19,
      "total": {
        "original": 218112000,
        "pruned": 213442560,
        "reduced": 4669440,
        "reduction_ratio": 0.02140845070422535
      },
      "attention": {
        "original": 41943040,
        "pruned": 41943040,
        "reduced": 0,
        "reduction_ratio": 0.0
      },
      "mlp": {
        "original": 176160768,
        "pruned": 171491328,
        "reduced": 4669440,
        "reduction_ratio": 0.026506696428571428,
        "intermediate_size": {
          "original": 14336,
          "pruned": 13956
        }
      },
      "is_zero_layer": false
    },
    {
      "layer_idx": 20,
      "total": {
        "original": 218112000,
        "pruned": 212803584,
        "reduced": 5308416,
        "reduction_ratio": 0.024338028169014085
      },
      "attention": {
        "original": 41943040,
        "pruned": 41943040,
        "reduced": 0,
        "reduction_ratio": 0.0
      },
      "mlp": {
        "original": 176160768,
        "pruned": 170852352,
        "reduced": 5308416,
        "reduction_ratio": 0.030133928571428572,
        "intermediate_size": {
          "original": 14336,
          "pruned": 13904
        }
      },
      "is_zero_layer": false
    },
    {
      "layer_idx": 21,
      "total": {
        "original": 218112000,
        "pruned": 210751488,
        "reduced": 7360512,
        "reduction_ratio": 0.033746478873239436
      },
      "attention": {
        "original": 41943040,
        "pruned": 41943040,
        "reduced": 0,
        "reduction_ratio": 0.0
      },
      "mlp": {
        "original": 176160768,
        "pruned": 168800256,
        "reduced": 7360512,
        "reduction_ratio": 0.041782924107142856,
        "intermediate_size": {
          "original": 14336,
          "pruned": 13737
        }
      },
      "is_zero_layer": false
    },
    {
      "layer_idx": 22,
      "total": {
        "original": 218112000,
        "pruned": 206721024,
        "reduced": 11390976,
        "reduction_ratio": 0.05222535211267606
      },
      "attention": {
        "original": 41943040,
        "pruned": 41943040,
        "reduced": 0,
        "reduction_ratio": 0.0
      },
      "mlp": {
        "original": 176160768,
        "pruned": 164769792,
        "reduced": 11390976,
        "reduction_ratio": 0.06466238839285714,
        "intermediate_size": {
          "original": 14336,
          "pruned": 13409
        }
      },
      "is_zero_layer": false
    },
    {
      "layer_idx": 23,
      "total": {
        "original": 218112000,
        "pruned": 208392192,
        "reduced": 9719808,
        "reduction_ratio": 0.04456338028169014
      },
      "attention": {
        "original": 41943040,
        "pruned": 41943040,
        "reduced": 0,
        "reduction_ratio": 0.0
      },
      "mlp": {
        "original": 176160768,
        "pruned": 166440960,
        "reduced": 9719808,
        "reduction_ratio": 0.05517578125,
        "intermediate_size": {
          "original": 14336,
          "pruned": 13545
        }
      },
      "is_zero_layer": false
    },
    {
      "layer_idx": 24,
      "total": {
        "original": 218112000,
        "pruned": 210518016,
        "reduced": 7593984,
        "reduction_ratio": 0.0348169014084507
      },
      "attention": {
        "original": 41943040,
        "pruned": 41943040,
        "reduced": 0,
        "reduction_ratio": 0.0
      },
      "mlp": {
        "original": 176160768,
        "pruned": 168566784,
        "reduced": 7593984,
        "reduction_ratio": 0.04310825892857143,
        "intermediate_size": {
          "original": 14336,
          "pruned": 13718
        }
      },
      "is_zero_layer": false
    },
    {
      "layer_idx": 25,
      "total": {
        "original": 218112000,
        "pruned": 210948096,
        "reduced": 7163904,
        "reduction_ratio": 0.03284507042253521
      },
      "attention": {
        "original": 41943040,
        "pruned": 41943040,
        "reduced": 0,
        "reduction_ratio": 0.0
      },
      "mlp": {
        "original": 176160768,
        "pruned": 168996864,
        "reduced": 7163904,
        "reduction_ratio": 0.04066685267857143,
        "intermediate_size": {
          "original": 14336,
          "pruned": 13753
        }
      },
      "is_zero_layer": false
    },
    {
      "layer_idx": 26,
      "total": {
        "original": 218112000,
        "pruned": 211550208,
        "reduced": 6561792,
        "reduction_ratio": 0.03008450704225352
      },
      "attention": {
        "original": 41943040,
        "pruned": 41943040,
        "reduced": 0,
        "reduction_ratio": 0.0
      },
      "mlp": {
        "original": 176160768,
        "pruned": 169598976,
        "reduced": 6561792,
        "reduction_ratio": 0.03724888392857143,
        "intermediate_size": {
          "original": 14336,
          "pruned": 13802
        }
      },
      "is_zero_layer": false
    },
    {
      "layer_idx": 27,
      "total": {
        "original": 218112000,
        "pruned": 212201472,
        "reduced": 5910528,
        "reduction_ratio": 0.027098591549295774
      },
      "attention": {
        "original": 41943040,
        "pruned": 41943040,
        "reduced": 0,
        "reduction_ratio": 0.0
      },
      "mlp": {
        "original": 176160768,
        "pruned": 170250240,
        "reduced": 5910528,
        "reduction_ratio": 0.03355189732142857,
        "intermediate_size": {
          "original": 14336,
          "pruned": 13855
        }
      },
      "is_zero_layer": false
    },
    {
      "layer_idx": 28,
      "total": {
        "original": 218112000,
        "pruned": 212754432,
        "reduced": 5357568,
        "reduction_ratio": 0.02456338028169014
      },
      "attention": {
        "original": 41943040,
        "pruned": 41943040,
        "reduced": 0,
        "reduction_ratio": 0.0
      },
      "mlp": {
        "original": 176160768,
        "pruned": 170803200,
        "reduced": 5357568,
        "reduction_ratio": 0.030412946428571428,
        "intermediate_size": {
          "original": 14336,
          "pruned": 13900
        }
      },
      "is_zero_layer": false
    },
    {
      "layer_idx": 29,
      "total": {
        "original": 218112000,
        "pruned": 210800640,
        "reduced": 7311360,
        "reduction_ratio": 0.03352112676056338
      },
      "attention": {
        "original": 41943040,
        "pruned": 41943040,
        "reduced": 0,
        "reduction_ratio": 0.0
      },
      "mlp": {
        "original": 176160768,
        "pruned": 168849408,
        "reduced": 7311360,
        "reduction_ratio": 0.04150390625,
        "intermediate_size": {
          "original": 14336,
          "pruned": 13741
        }
      },
      "is_zero_layer": false
    },
    {
      "layer_idx": 30,
      "total": {
        "original": 218112000,
        "pruned": 210309120,
        "reduced": 7802880,
        "reduction_ratio": 0.03577464788732394
      },
      "attention": {
        "original": 41943040,
        "pruned": 41943040,
        "reduced": 0,
        "reduction_ratio": 0.0
      },
      "mlp": {
        "original": 176160768,
        "pruned": 168357888,
        "reduced": 7802880,
        "reduction_ratio": 0.04429408482142857,
        "intermediate_size": {
          "original": 14336,
          "pruned": 13701
        }
      },
      "is_zero_layer": false
    },
    {
      "layer_idx": 31,
      "total": {
        "original": 218112000,
        "pruned": 200724480,
        "reduced": 17387520,
        "reduction_ratio": 0.07971830985915493
      },
      "attention": {
        "original": 41943040,
        "pruned": 41943040,
        "reduced": 0,
        "reduction_ratio": 0.0
      },
      "mlp": {
        "original": 176160768,
        "pruned": 158773248,
        "reduced": 17387520,
        "reduction_ratio": 0.09870256696428571,
        "intermediate_size": {
          "original": 14336,
          "pruned": 12921
        }
      },
      "is_zero_layer": false
    }
  ]
}