{
  "model_name": "剪枝后模型",
  "total_params": 6092498944,
  "embedding_params": 544997376,
  "lm_head_params": 544997376,
  "layers": [
    {
      "layer_idx": 0,
      "total": 190447616,
      "attention": {
        "type": "LlamaAttention",
        "q_proj": 12848640,
        "k_proj": 1835520,
        "v_proj": 1835520,
        "o_proj": 12845056,
        "total": 29364736
      },
      "mlp": {
        "type": "LlamaMLP",
        "gate_proj": 53691904,
        "up_proj": 53691904,
        "down_proj": 53691904,
        "total": 161075712,
        "intermediate_size": 14981
      },
      "norm": 7168,
      "is_zero_layer": false
    },
    {
      "layer_idx": 1,
      "total": 80680448,
      "attention": {
        "type": "LlamaAttention",
        "q_proj": 12848640,
        "k_proj": 1835520,
        "v_proj": 1835520,
        "o_proj": 12845056,
        "total": 29364736
      },
      "mlp": {
        "type": "LlamaMLP",
        "gate_proj": 17102848,
        "up_proj": 17102848,
        "down_proj": 17102848,
        "total": 51308544,
        "intermediate_size": 4772
      },
      "norm": 7168,
      "is_zero_layer": false
    },
    {
      "layer_idx": 2,
      "total": 140644352,
      "attention": {
        "type": "LlamaAttention",
        "q_proj": 12848640,
        "k_proj": 1835520,
        "v_proj": 1835520,
        "o_proj": 12845056,
        "total": 29364736
      },
      "mlp": {
        "type": "LlamaMLP",
        "gate_proj": 37090816,
        "up_proj": 37090816,
        "down_proj": 37090816,
        "total": 111272448,
        "intermediate_size": 10349
      },
      "norm": 7168,
      "is_zero_layer": false
    },
    {
      "layer_idx": 3,
      "total": 228412928,
      "attention": {
        "type": "LlamaAttention",
        "q_proj": 12848640,
        "k_proj": 1835520,
        "v_proj": 1835520,
        "o_proj": 12845056,
        "total": 29364736
      },
      "mlp": {
        "type": "LlamaMLP",
        "gate_proj": 66347008,
        "up_proj": 66347008,
        "down_proj": 66347008,
        "total": 199041024,
        "intermediate_size": 18512
      },
      "norm": 7168,
      "is_zero_layer": false
    },
    {
      "layer_idx": 4,
      "total": 230767616,
      "attention": {
        "type": "LlamaAttention",
        "q_proj": 12848640,
        "k_proj": 1835520,
        "v_proj": 1835520,
        "o_proj": 12845056,
        "total": 29364736
      },
      "mlp": {
        "type": "LlamaMLP",
        "gate_proj": 67131904,
        "up_proj": 67131904,
        "down_proj": 67131904,
        "total": 201395712,
        "intermediate_size": 18731
      },
      "norm": 7168,
      "is_zero_layer": false
    },
    {
      "layer_idx": 5,
      "total": 105807872,
      "attention": {
        "type": "LlamaAttention",
        "q_proj": 12848640,
        "k_proj": 1835520,
        "v_proj": 1835520,
        "o_proj": 12845056,
        "total": 29364736
      },
      "mlp": {
        "type": "LlamaMLP",
        "gate_proj": 25478656,
        "up_proj": 25478656,
        "down_proj": 25478656,
        "total": 76435968,
        "intermediate_size": 7109
      },
      "norm": 7168,
      "is_zero_layer": false
    },
    {
      "layer_idx": 6,
      "total": 216295424,
      "attention": {
        "type": "LlamaAttention",
        "q_proj": 12848640,
        "k_proj": 1835520,
        "v_proj": 1835520,
        "o_proj": 12845056,
        "total": 29364736
      },
      "mlp": {
        "type": "LlamaMLP",
        "gate_proj": 62307840,
        "up_proj": 62307840,
        "down_proj": 62307840,
        "total": 186923520,
        "intermediate_size": 17385
      },
      "norm": 7168,
      "is_zero_layer": false
    },
    {
      "layer_idx": 7,
      "total": 225595904,
      "attention": {
        "type": "LlamaAttention",
        "q_proj": 12848640,
        "k_proj": 1835520,
        "v_proj": 1835520,
        "o_proj": 12845056,
        "total": 29364736
      },
      "mlp": {
        "type": "LlamaMLP",
        "gate_proj": 65408000,
        "up_proj": 65408000,
        "down_proj": 65408000,
        "total": 196224000,
        "intermediate_size": 18250
      },
      "norm": 7168,
      "is_zero_layer": false
    },
    {
      "layer_idx": 8,
      "total": 209586176,
      "attention": {
        "type": "LlamaAttention",
        "q_proj": 12848640,
        "k_proj": 1835520,
        "v_proj": 1835520,
        "o_proj": 12845056,
        "total": 29364736
      },
      "mlp": {
        "type": "LlamaMLP",
        "gate_proj": 60071424,
        "up_proj": 60071424,
        "down_proj": 60071424,
        "total": 180214272,
        "intermediate_size": 16761
      },
      "norm": 7168,
      "is_zero_layer": false
    },
    {
      "layer_idx": 9,
      "total": 232896512,
      "attention": {
        "type": "LlamaAttention",
        "q_proj": 12848640,
        "k_proj": 1835520,
        "v_proj": 1835520,
        "o_proj": 12845056,
        "total": 29364736
      },
      "mlp": {
        "type": "LlamaMLP",
        "gate_proj": 67841536,
        "up_proj": 67841536,
        "down_proj": 67841536,
        "total": 203524608,
        "intermediate_size": 18929
      },
      "norm": 7168,
      "is_zero_layer": false
    },
    {
      "layer_idx": 10,
      "total": 210231296,
      "attention": {
        "type": "LlamaAttention",
        "q_proj": 12848640,
        "k_proj": 1835520,
        "v_proj": 1835520,
        "o_proj": 12845056,
        "total": 29364736
      },
      "mlp": {
        "type": "LlamaMLP",
        "gate_proj": 60286464,
        "up_proj": 60286464,
        "down_proj": 60286464,
        "total": 180859392,
        "intermediate_size": 16821
      },
      "norm": 7168,
      "is_zero_layer": false
    },
    {
      "layer_idx": 11,
      "total": 201758720,
      "attention": {
        "type": "LlamaAttention",
        "q_proj": 12848640,
        "k_proj": 1835520,
        "v_proj": 1835520,
        "o_proj": 12845056,
        "total": 29364736
      },
      "mlp": {
        "type": "LlamaMLP",
        "gate_proj": 57462272,
        "up_proj": 57462272,
        "down_proj": 57462272,
        "total": 172386816,
        "intermediate_size": 16033
      },
      "norm": 7168,
      "is_zero_layer": false
    },
    {
      "layer_idx": 12,
      "total": 176491520,
      "attention": {
        "type": "LlamaAttention",
        "q_proj": 12848640,
        "k_proj": 1835520,
        "v_proj": 1835520,
        "o_proj": 12845056,
        "total": 29364736
      },
      "mlp": {
        "type": "LlamaMLP",
        "gate_proj": 49039872,
        "up_proj": 49039872,
        "down_proj": 49039872,
        "total": 147119616,
        "intermediate_size": 13683
      },
      "norm": 7168,
      "is_zero_layer": false
    },
    {
      "layer_idx": 13,
      "total": 156256256,
      "attention": {
        "type": "LlamaAttention",
        "q_proj": 12848640,
        "k_proj": 1835520,
        "v_proj": 1835520,
        "o_proj": 12845056,
        "total": 29364736
      },
      "mlp": {
        "type": "LlamaMLP",
        "gate_proj": 42294784,
        "up_proj": 42294784,
        "down_proj": 42294784,
        "total": 126884352,
        "intermediate_size": 11801
      },
      "norm": 7168,
      "is_zero_layer": false
    },
    {
      "layer_idx": 14,
      "total": 184684544,
      "attention": {
        "type": "LlamaAttention",
        "q_proj": 12848640,
        "k_proj": 1835520,
        "v_proj": 1835520,
        "o_proj": 12845056,
        "total": 29364736
      },
      "mlp": {
        "type": "LlamaMLP",
        "gate_proj": 51770880,
        "up_proj": 51770880,
        "down_proj": 51770880,
        "total": 155312640,
        "intermediate_size": 14445
      },
      "norm": 7168,
      "is_zero_layer": false
    },
    {
      "layer_idx": 15,
      "total": 170244608,
      "attention": {
        "type": "LlamaAttention",
        "q_proj": 12848640,
        "k_proj": 1835520,
        "v_proj": 1835520,
        "o_proj": 12845056,
        "total": 29364736
      },
      "mlp": {
        "type": "LlamaMLP",
        "gate_proj": 46957568,
        "up_proj": 46957568,
        "down_proj": 46957568,
        "total": 140872704,
        "intermediate_size": 13102
      },
      "norm": 7168,
      "is_zero_layer": false
    },
    {
      "layer_idx": 16,
      "total": 94905344,
      "attention": {
        "type": "LlamaAttention",
        "q_proj": 12848640,
        "k_proj": 1835520,
        "v_proj": 1835520,
        "o_proj": 12845056,
        "total": 29364736
      },
      "mlp": {
        "type": "LlamaMLP",
        "gate_proj": 21844480,
        "up_proj": 21844480,
        "down_proj": 21844480,
        "total": 65533440,
        "intermediate_size": 6095
      },
      "norm": 7168,
      "is_zero_layer": false
    },
    {
      "layer_idx": 17,
      "total": 66853376,
      "attention": {
        "type": "LlamaAttention",
        "q_proj": 12848640,
        "k_proj": 1835520,
        "v_proj": 1835520,
        "o_proj": 12845056,
        "total": 29364736
      },
      "mlp": {
        "type": "LlamaMLP",
        "gate_proj": 12493824,
        "up_proj": 12493824,
        "down_proj": 12493824,
        "total": 37481472,
        "intermediate_size": 3486
      },
      "norm": 7168,
      "is_zero_layer": false
    },
    {
      "layer_idx": 18,
      "total": 130440704,
      "attention": {
        "type": "LlamaAttention",
        "q_proj": 12848640,
        "k_proj": 1835520,
        "v_proj": 1835520,
        "o_proj": 12845056,
        "total": 29364736
      },
      "mlp": {
        "type": "LlamaMLP",
        "gate_proj": 33689600,
        "up_proj": 33689600,
        "down_proj": 33689600,
        "total": 101068800,
        "intermediate_size": 9400
      },
      "norm": 7168,
      "is_zero_layer": false
    },
    {
      "layer_idx": 19,
      "total": 221488640,
      "attention": {
        "type": "LlamaAttention",
        "q_proj": 12848640,
        "k_proj": 1835520,
        "v_proj": 1835520,
        "o_proj": 12845056,
        "total": 29364736
      },
      "mlp": {
        "type": "LlamaMLP",
        "gate_proj": 64038912,
        "up_proj": 64038912,
        "down_proj": 64038912,
        "total": 192116736,
        "intermediate_size": 17868
      },
      "norm": 7168,
      "is_zero_layer": false
    },
    {
      "layer_idx": 20,
      "total": 178512896,
      "attention": {
        "type": "LlamaAttention",
        "q_proj": 12848640,
        "k_proj": 1835520,
        "v_proj": 1835520,
        "o_proj": 12845056,
        "total": 29364736
      },
      "mlp": {
        "type": "LlamaMLP",
        "gate_proj": 49713664,
        "up_proj": 49713664,
        "down_proj": 49713664,
        "total": 149140992,
        "intermediate_size": 13871
      },
      "norm": 7168,
      "is_zero_layer": false
    },
    {
      "layer_idx": 21,
      "total": 184899584,
      "attention": {
        "type": "LlamaAttention",
        "q_proj": 12848640,
        "k_proj": 1835520,
        "v_proj": 1835520,
        "o_proj": 12845056,
        "total": 29364736
      },
      "mlp": {
        "type": "LlamaMLP",
        "gate_proj": 51842560,
        "up_proj": 51842560,
        "down_proj": 51842560,
        "total": 155527680,
        "intermediate_size": 14465
      },
      "norm": 7168,
      "is_zero_layer": false
    },
    {
      "layer_idx": 22,
      "total": 207726080,
      "attention": {
        "type": "LlamaAttention",
        "q_proj": 12848640,
        "k_proj": 1835520,
        "v_proj": 1835520,
        "o_proj": 12845056,
        "total": 29364736
      },
      "mlp": {
        "type": "LlamaMLP",
        "gate_proj": 59451392,
        "up_proj": 59451392,
        "down_proj": 59451392,
        "total": 178354176,
        "intermediate_size": 16588
      },
      "norm": 7168,
      "is_zero_layer": false
    },
    {
      "layer_idx": 23,
      "total": 211037696,
      "attention": {
        "type": "LlamaAttention",
        "q_proj": 12848640,
        "k_proj": 1835520,
        "v_proj": 1835520,
        "o_proj": 12845056,
        "total": 29364736
      },
      "mlp": {
        "type": "LlamaMLP",
        "gate_proj": 60555264,
        "up_proj": 60555264,
        "down_proj": 60555264,
        "total": 181665792,
        "intermediate_size": 16896
      },
      "norm": 7168,
      "is_zero_layer": false
    },
    {
      "layer_idx": 24,
      "total": 186168320,
      "attention": {
        "type": "LlamaAttention",
        "q_proj": 12848640,
        "k_proj": 1835520,
        "v_proj": 1835520,
        "o_proj": 12845056,
        "total": 29364736
      },
      "mlp": {
        "type": "LlamaMLP",
        "gate_proj": 52265472,
        "up_proj": 52265472,
        "down_proj": 52265472,
        "total": 156796416,
        "intermediate_size": 14583
      },
      "norm": 7168,
      "is_zero_layer": false
    },
    {
      "layer_idx": 25,
      "total": 175717376,
      "attention": {
        "type": "LlamaAttention",
        "q_proj": 12848640,
        "k_proj": 1835520,
        "v_proj": 1835520,
        "o_proj": 12845056,
        "total": 29364736
      },
      "mlp": {
        "type": "LlamaMLP",
        "gate_proj": 48781824,
        "up_proj": 48781824,
        "down_proj": 48781824,
        "total": 146345472,
        "intermediate_size": 13611
      },
      "norm": 7168,
      "is_zero_layer": false
    },
    {
      "layer_idx": 26,
      "total": 157503488,
      "attention": {
        "type": "LlamaAttention",
        "q_proj": 12848640,
        "k_proj": 1835520,
        "v_proj": 1835520,
        "o_proj": 12845056,
        "total": 29364736
      },
      "mlp": {
        "type": "LlamaMLP",
        "gate_proj": 42710528,
        "up_proj": 42710528,
        "down_proj": 42710528,
        "total": 128131584,
        "intermediate_size": 11917
      },
      "norm": 7168,
      "is_zero_layer": false
    },
    {
      "layer_idx": 27,
      "total": 226445312,
      "attention": {
        "type": "LlamaAttention",
        "q_proj": 12848640,
        "k_proj": 1835520,
        "v_proj": 1835520,
        "o_proj": 12845056,
        "total": 29364736
      },
      "mlp": {
        "type": "LlamaMLP",
        "gate_proj": 65691136,
        "up_proj": 65691136,
        "down_proj": 65691136,
        "total": 197073408,
        "intermediate_size": 18329
      },
      "norm": 7168,
      "is_zero_layer": false
    }
  ],
  "layer_summary": {
    "num_layers": 28,
    "total_layer_params": 5002500608
  }
}