{
  "extreme_pruning_layers": [
    {
      "layer_idx": 0,
      "pruning_rate": 0.5882601351351351,
      "importance": 0.0033895242613161333,
      "gradient_mean": 0.0004131495952606201,
      "gradient_norm": 0.31344350179036456
    },
    {
      "layer_idx": 1,
      "pruning_rate": 0.6602618243243243,
      "importance": 0.0019270912335078057,
      "gradient_mean": 0.00029564400513966876,
      "gradient_norm": 0.34904972712198895
    }
  ],
  "num_extreme_layers": 2,
  "gradient_statistics": {
    "mean_range": [
      0.00011505186557769775,
      0.0004131495952606201
    ],
    "mean_ratio": 3.5909825024380733,
    "norm_range": [
      0.30913782119750977,
      0.8592647711435953
    ],
    "norm_ratio": 2.779552393612334
  },
  "diagnosis": [
    {
      "issue": "\u524d\u51e0\u5c42\u88ab\u8fc7\u5ea6\u526a\u679d",
      "severity": "critical",
      "description": "\u524d5\u5c42\u4e2d\u6709 2 \u5c42\u88ab\u8fc7\u5ea6\u526a\u679d",
      "recommendation": "\u524d\u51e0\u5c42\u901a\u5e38\u5f88\u91cd\u8981\uff0c\u5efa\u8bae\u4e3a\u5176\u8bbe\u7f6e\u8f83\u4f4e\u7684 max_rate"
    }
  ]
}