{
  "model_name": "剪枝后模型",
  "total_params": 6424215552,
  "embedding_params": 525336576,
  "lm_head_params": 525336576,
  "layers": [
    {
      "layer_idx": 0,
      "total": 218112000,
      "attention": {
        "type": "LlamaAttention",
        "q_proj": 16777216,
        "k_proj": 4194304,
        "v_proj": 4194304,
        "o_proj": 16777216,
        "total": 41943040
      },
      "mlp": {
        "type": "LlamaMLP",
        "gate_proj": 58720256,
        "up_proj": 58720256,
        "down_proj": 58720256,
        "total": 176160768,
        "intermediate_size": 14336
      },
      "norm": 8192,
      "is_zero_layer": false
    },
    {
      "layer_idx": 1,
      "total": 218112000,
      "attention": {
        "type": "LlamaAttention",
        "q_proj": 16777216,
        "k_proj": 4194304,
        "v_proj": 4194304,
        "o_proj": 16777216,
        "total": 41943040
      },
      "mlp": {
        "type": "LlamaMLP",
        "gate_proj": 58720256,
        "up_proj": 58720256,
        "down_proj": 58720256,
        "total": 176160768,
        "intermediate_size": 14336
      },
      "norm": 8192,
      "is_zero_layer": false
    },
    {
      "layer_idx": 2,
      "total": 218099712,
      "attention": {
        "type": "LlamaAttention",
        "q_proj": 16777216,
        "k_proj": 4194304,
        "v_proj": 4194304,
        "o_proj": 16777216,
        "total": 41943040
      },
      "mlp": {
        "type": "LlamaMLP",
        "gate_proj": 58716160,
        "up_proj": 58716160,
        "down_proj": 58716160,
        "total": 176148480,
        "intermediate_size": 14335
      },
      "norm": 8192,
      "is_zero_layer": false
    },
    {
      "layer_idx": 3,
      "total": 217669632,
      "attention": {
        "type": "LlamaAttention",
        "q_proj": 16777216,
        "k_proj": 4194304,
        "v_proj": 4194304,
        "o_proj": 16777216,
        "total": 41943040
      },
      "mlp": {
        "type": "LlamaMLP",
        "gate_proj": 58572800,
        "up_proj": 58572800,
        "down_proj": 58572800,
        "total": 175718400,
        "intermediate_size": 14300
      },
      "norm": 8192,
      "is_zero_layer": false
    },
    {
      "layer_idx": 4,
      "total": 215617536,
      "attention": {
        "type": "LlamaAttention",
        "q_proj": 16777216,
        "k_proj": 4194304,
        "v_proj": 4194304,
        "o_proj": 16777216,
        "total": 41943040
      },
      "mlp": {
        "type": "LlamaMLP",
        "gate_proj": 57888768,
        "up_proj": 57888768,
        "down_proj": 57888768,
        "total": 173666304,
        "intermediate_size": 14133
      },
      "norm": 8192,
      "is_zero_layer": false
    },
    {
      "layer_idx": 5,
      "total": 213270528,
      "attention": {
        "type": "LlamaAttention",
        "q_proj": 16777216,
        "k_proj": 4194304,
        "v_proj": 4194304,
        "o_proj": 16777216,
        "total": 41943040
      },
      "mlp": {
        "type": "LlamaMLP",
        "gate_proj": 57106432,
        "up_proj": 57106432,
        "down_proj": 57106432,
        "total": 171319296,
        "intermediate_size": 13942
      },
      "norm": 8192,
      "is_zero_layer": false
    },
    {
      "layer_idx": 6,
      "total": 208527360,
      "attention": {
        "type": "LlamaAttention",
        "q_proj": 16777216,
        "k_proj": 4194304,
        "v_proj": 4194304,
        "o_proj": 16777216,
        "total": 41943040
      },
      "mlp": {
        "type": "LlamaMLP",
        "gate_proj": 55525376,
        "up_proj": 55525376,
        "down_proj": 55525376,
        "total": 166576128,
        "intermediate_size": 13556
      },
      "norm": 8192,
      "is_zero_layer": false
    },
    {
      "layer_idx": 7,
      "total": 202235904,
      "attention": {
        "type": "LlamaAttention",
        "q_proj": 16777216,
        "k_proj": 4194304,
        "v_proj": 4194304,
        "o_proj": 16777216,
        "total": 41943040
      },
      "mlp": {
        "type": "LlamaMLP",
        "gate_proj": 53428224,
        "up_proj": 53428224,
        "down_proj": 53428224,
        "total": 160284672,
        "intermediate_size": 13044
      },
      "norm": 8192,
      "is_zero_layer": false
    },
    {
      "layer_idx": 8,
      "total": 198389760,
      "attention": {
        "type": "LlamaAttention",
        "q_proj": 16777216,
        "k_proj": 4194304,
        "v_proj": 4194304,
        "o_proj": 16777216,
        "total": 41943040
      },
      "mlp": {
        "type": "LlamaMLP",
        "gate_proj": 52146176,
        "up_proj": 52146176,
        "down_proj": 52146176,
        "total": 156438528,
        "intermediate_size": 12731
      },
      "norm": 8192,
      "is_zero_layer": false
    },
    {
      "layer_idx": 9,
      "total": 197824512,
      "attention": {
        "type": "LlamaAttention",
        "q_proj": 16777216,
        "k_proj": 4194304,
        "v_proj": 4194304,
        "o_proj": 16777216,
        "total": 41943040
      },
      "mlp": {
        "type": "LlamaMLP",
        "gate_proj": 51957760,
        "up_proj": 51957760,
        "down_proj": 51957760,
        "total": 155873280,
        "intermediate_size": 12685
      },
      "norm": 8192,
      "is_zero_layer": false
    },
    {
      "layer_idx": 10,
      "total": 191938560,
      "attention": {
        "type": "LlamaAttention",
        "q_proj": 16777216,
        "k_proj": 4194304,
        "v_proj": 4194304,
        "o_proj": 16777216,
        "total": 41943040
      },
      "mlp": {
        "type": "LlamaMLP",
        "gate_proj": 49995776,
        "up_proj": 49995776,
        "down_proj": 49995776,
        "total": 149987328,
        "intermediate_size": 12206
      },
      "norm": 8192,
      "is_zero_layer": false
    },
    {
      "layer_idx": 11,
      "total": 191938560,
      "attention": {
        "type": "LlamaAttention",
        "q_proj": 16777216,
        "k_proj": 4194304,
        "v_proj": 4194304,
        "o_proj": 16777216,
        "total": 41943040
      },
      "mlp": {
        "type": "LlamaMLP",
        "gate_proj": 49995776,
        "up_proj": 49995776,
        "down_proj": 49995776,
        "total": 149987328,
        "intermediate_size": 12206
      },
      "norm": 8192,
      "is_zero_layer": false
    },
    {
      "layer_idx": 12,
      "total": 186421248,
      "attention": {
        "type": "LlamaAttention",
        "q_proj": 16777216,
        "k_proj": 4194304,
        "v_proj": 4194304,
        "o_proj": 16777216,
        "total": 41943040
      },
      "mlp": {
        "type": "LlamaMLP",
        "gate_proj": 48156672,
        "up_proj": 48156672,
        "down_proj": 48156672,
        "total": 144470016,
        "intermediate_size": 11757
      },
      "norm": 8192,
      "is_zero_layer": false
    },
    {
      "layer_idx": 13,
      "total": 180867072,
      "attention": {
        "type": "LlamaAttention",
        "q_proj": 16777216,
        "k_proj": 4194304,
        "v_proj": 4194304,
        "o_proj": 16777216,
        "total": 41943040
      },
      "mlp": {
        "type": "LlamaMLP",
        "gate_proj": 46305280,
        "up_proj": 46305280,
        "down_proj": 46305280,
        "total": 138915840,
        "intermediate_size": 11305
      },
      "norm": 8192,
      "is_zero_layer": false
    },
    {
      "layer_idx": 14,
      "total": 188633088,
      "attention": {
        "type": "LlamaAttention",
        "q_proj": 16777216,
        "k_proj": 4194304,
        "v_proj": 4194304,
        "o_proj": 16777216,
        "total": 41943040
      },
      "mlp": {
        "type": "LlamaMLP",
        "gate_proj": 48893952,
        "up_proj": 48893952,
        "down_proj": 48893952,
        "total": 146681856,
        "intermediate_size": 11937
      },
      "norm": 8192,
      "is_zero_layer": false
    },
    {
      "layer_idx": 15,
      "total": 183656448,
      "attention": {
        "type": "LlamaAttention",
        "q_proj": 16777216,
        "k_proj": 4194304,
        "v_proj": 4194304,
        "o_proj": 16777216,
        "total": 41943040
      },
      "mlp": {
        "type": "LlamaMLP",
        "gate_proj": 47235072,
        "up_proj": 47235072,
        "down_proj": 47235072,
        "total": 141705216,
        "intermediate_size": 11532
      },
      "norm": 8192,
      "is_zero_layer": false
    },
    {
      "layer_idx": 16,
      "total": 173346816,
      "attention": {
        "type": "LlamaAttention",
        "q_proj": 16777216,
        "k_proj": 4194304,
        "v_proj": 4194304,
        "o_proj": 16777216,
        "total": 41943040
      },
      "mlp": {
        "type": "LlamaMLP",
        "gate_proj": 43798528,
        "up_proj": 43798528,
        "down_proj": 43798528,
        "total": 131395584,
        "intermediate_size": 10693
      },
      "norm": 8192,
      "is_zero_layer": false
    },
    {
      "layer_idx": 17,
      "total": 171442176,
      "attention": {
        "type": "LlamaAttention",
        "q_proj": 16777216,
        "k_proj": 4194304,
        "v_proj": 4194304,
        "o_proj": 16777216,
        "total": 41943040
      },
      "mlp": {
        "type": "LlamaMLP",
        "gate_proj": 43163648,
        "up_proj": 43163648,
        "down_proj": 43163648,
        "total": 129490944,
        "intermediate_size": 10538
      },
      "norm": 8192,
      "is_zero_layer": false
    },
    {
      "layer_idx": 18,
      "total": 160264192,
      "attention": {
        "type": "LlamaAttention",
        "q_proj": 14680064,
        "k_proj": 3670016,
        "v_proj": 3670016,
        "o_proj": 14680064,
        "total": 36700160,
        "num_heads": 28,
        "num_kv_heads": 7
      },
      "mlp": {
        "type": "LlamaMLP",
        "gate_proj": 41185280,
        "up_proj": 41185280,
        "down_proj": 41185280,
        "total": 123555840,
        "intermediate_size": 10055
      },
      "norm": 8192,
      "is_zero_layer": false
    },
    {
      "layer_idx": 19,
      "total": 150925312,
      "attention": {
        "type": "LlamaAttention",
        "q_proj": 14680064,
        "k_proj": 3670016,
        "v_proj": 3670016,
        "o_proj": 14680064,
        "total": 36700160,
        "num_heads": 28,
        "num_kv_heads": 7
      },
      "mlp": {
        "type": "LlamaMLP",
        "gate_proj": 38072320,
        "up_proj": 38072320,
        "down_proj": 38072320,
        "total": 114216960,
        "intermediate_size": 9295
      },
      "norm": 8192,
      "is_zero_layer": false
    },
    {
      "layer_idx": 20,
      "total": 142401536,
      "attention": {
        "type": "LlamaAttention",
        "q_proj": 12582912,
        "k_proj": 3145728,
        "v_proj": 3145728,
        "o_proj": 12582912,
        "total": 31457280,
        "num_heads": 24,
        "num_kv_heads": 6
      },
      "mlp": {
        "type": "LlamaMLP",
        "gate_proj": 36978688,
        "up_proj": 36978688,
        "down_proj": 36978688,
        "total": 110936064,
        "intermediate_size": 9028
      },
      "norm": 8192,
      "is_zero_layer": false
    },
    {
      "layer_idx": 21,
      "total": 141438976,
      "attention": {
        "type": "LlamaAttention",
        "q_proj": 14680064,
        "k_proj": 3670016,
        "v_proj": 3670016,
        "o_proj": 14680064,
        "total": 36700160,
        "num_heads": 28,
        "num_kv_heads": 7
      },
      "mlp": {
        "type": "LlamaMLP",
        "gate_proj": 34910208,
        "up_proj": 34910208,
        "down_proj": 34910208,
        "total": 104730624,
        "intermediate_size": 8523
      },
      "norm": 8192,
      "is_zero_layer": false
    },
    {
      "layer_idx": 22,
      "total": 137191424,
      "attention": {
        "type": "LlamaAttention",
        "q_proj": 12582912,
        "k_proj": 3145728,
        "v_proj": 3145728,
        "o_proj": 12582912,
        "total": 31457280,
        "num_heads": 24,
        "num_kv_heads": 6
      },
      "mlp": {
        "type": "LlamaMLP",
        "gate_proj": 35241984,
        "up_proj": 35241984,
        "down_proj": 35241984,
        "total": 105725952,
        "intermediate_size": 8604
      },
      "norm": 8192,
      "is_zero_layer": false
    },
    {
      "layer_idx": 23,
      "total": 110432256,
      "attention": {
        "type": "LlamaAttention",
        "q_proj": 4194304,
        "k_proj": 1048576,
        "v_proj": 1048576,
        "o_proj": 4194304,
        "total": 10485760,
        "num_heads": 8,
        "num_kv_heads": 2
      },
      "mlp": {
        "type": "LlamaMLP",
        "gate_proj": 33312768,
        "up_proj": 33312768,
        "down_proj": 33312768,
        "total": 99938304,
        "intermediate_size": 8133
      },
      "norm": 8192,
      "is_zero_layer": false
    },
    {
      "layer_idx": 24,
      "total": 119169024,
      "attention": {
        "type": "LlamaAttention",
        "q_proj": 10485760,
        "k_proj": 2621440,
        "v_proj": 2621440,
        "o_proj": 10485760,
        "total": 26214400,
        "num_heads": 20,
        "num_kv_heads": 5
      },
      "mlp": {
        "type": "LlamaMLP",
        "gate_proj": 30982144,
        "up_proj": 30982144,
        "down_proj": 30982144,
        "total": 92946432,
        "intermediate_size": 7564
      },
      "norm": 8192,
      "is_zero_layer": false
    },
    {
      "layer_idx": 25,
      "total": 113795072,
      "attention": {
        "type": "LlamaAttention",
        "q_proj": 12582912,
        "k_proj": 3145728,
        "v_proj": 3145728,
        "o_proj": 12582912,
        "total": 31457280,
        "num_heads": 24,
        "num_kv_heads": 6
      },
      "mlp": {
        "type": "LlamaMLP",
        "gate_proj": 27443200,
        "up_proj": 27443200,
        "down_proj": 27443200,
        "total": 82329600,
        "intermediate_size": 6700
      },
      "norm": 8192,
      "is_zero_layer": false
    },
    {
      "layer_idx": 26,
      "total": 103108608,
      "attention": {
        "type": "LlamaAttention",
        "q_proj": 10485760,
        "k_proj": 2621440,
        "v_proj": 2621440,
        "o_proj": 10485760,
        "total": 26214400,
        "num_heads": 20,
        "num_kv_heads": 5
      },
      "mlp": {
        "type": "LlamaMLP",
        "gate_proj": 25628672,
        "up_proj": 25628672,
        "down_proj": 25628672,
        "total": 76886016,
        "intermediate_size": 6257
      },
      "norm": 8192,
      "is_zero_layer": false
    },
    {
      "layer_idx": 27,
      "total": 89161728,
      "attention": {
        "type": "LlamaAttention",
        "q_proj": 10485760,
        "k_proj": 2621440,
        "v_proj": 2621440,
        "o_proj": 10485760,
        "total": 26214400,
        "num_heads": 20,
        "num_kv_heads": 5
      },
      "mlp": {
        "type": "LlamaMLP",
        "gate_proj": 20979712,
        "up_proj": 20979712,
        "down_proj": 20979712,
        "total": 62939136,
        "intermediate_size": 5122
      },
      "norm": 8192,
      "is_zero_layer": false
    },
    {
      "layer_idx": 28,
      "total": 95592448,
      "attention": {
        "type": "LlamaAttention",
        "q_proj": 8388608,
        "k_proj": 2097152,
        "v_proj": 2097152,
        "o_proj": 8388608,
        "total": 20971520,
        "num_heads": 16,
        "num_kv_heads": 4
      },
      "mlp": {
        "type": "LlamaMLP",
        "gate_proj": 24870912,
        "up_proj": 24870912,
        "down_proj": 24870912,
        "total": 74612736,
        "intermediate_size": 6072
      },
      "norm": 8192,
      "is_zero_layer": false
    },
    {
      "layer_idx": 29,
      "total": 91697152,
      "attention": {
        "type": "LlamaAttention",
        "q_proj": 8388608,
        "k_proj": 2097152,
        "v_proj": 2097152,
        "o_proj": 8388608,
        "total": 20971520,
        "num_heads": 16,
        "num_kv_heads": 4
      },
      "mlp": {
        "type": "LlamaMLP",
        "gate_proj": 23572480,
        "up_proj": 23572480,
        "down_proj": 23572480,
        "total": 70717440,
        "intermediate_size": 5755
      },
      "norm": 8192,
      "is_zero_layer": false
    },
    {
      "layer_idx": 30,
      "total": 155774976,
      "attention": {
        "type": "LlamaAttention",
        "q_proj": 16777216,
        "k_proj": 4194304,
        "v_proj": 4194304,
        "o_proj": 16777216,
        "total": 41943040
      },
      "mlp": {
        "type": "LlamaMLP",
        "gate_proj": 37941248,
        "up_proj": 37941248,
        "down_proj": 37941248,
        "total": 113823744,
        "intermediate_size": 9263
      },
      "norm": 8192,
      "is_zero_layer": false
    },
    {
      "layer_idx": 31,
      "total": 186482688,
      "attention": {
        "type": "LlamaAttention",
        "q_proj": 10485760,
        "k_proj": 2621440,
        "v_proj": 2621440,
        "o_proj": 10485760,
        "total": 26214400,
        "num_heads": 20,
        "num_kv_heads": 5
      },
      "mlp": {
        "type": "LlamaMLP",
        "gate_proj": 53420032,
        "up_proj": 53420032,
        "down_proj": 53420032,
        "total": 160260096,
        "intermediate_size": 13042
      },
      "norm": 8192,
      "is_zero_layer": false
    }
  ],
  "layer_summary": {
    "num_layers": 32,
    "total_layer_params": 5373538304
  }
}