{
  "original_name": "原始模型",
  "pruned_name": "剪枝后模型",
  "total_params": {
    "original": 8030261248,
    "pruned": 6424219648,
    "reduced": 1606041600,
    "reduction_ratio": 0.199998673816496
  },
  "layer_params": {
    "original": 6979584000,
    "pruned": 5373542400,
    "reduced": 1606041600,
    "reduction_ratio": 0.2301056338028169
  },
  "layers": [
    {
      "layer_idx": 0,
      "total": {
        "original": 218112000,
        "pruned": 218062848,
        "reduced": 49152,
        "reduction_ratio": 0.00022535211267605634
      },
      "attention": {
        "original": 41943040,
        "pruned": 41943040,
        "reduced": 0,
        "reduction_ratio": 0.0
      },
      "mlp": {
        "original": 176160768,
        "pruned": 176111616,
        "reduced": 49152,
        "reduction_ratio": 0.00027901785714285713,
        "intermediate_size": {
          "original": 14336,
          "pruned": 14332
        }
      },
      "is_zero_layer": false
    },
    {
      "layer_idx": 1,
      "total": {
        "original": 218112000,
        "pruned": 218075136,
        "reduced": 36864,
        "reduction_ratio": 0.00016901408450704225
      },
      "attention": {
        "original": 41943040,
        "pruned": 41943040,
        "reduced": 0,
        "reduction_ratio": 0.0
      },
      "mlp": {
        "original": 176160768,
        "pruned": 176123904,
        "reduced": 36864,
        "reduction_ratio": 0.00020926339285714285,
        "intermediate_size": {
          "original": 14336,
          "pruned": 14333
        }
      },
      "is_zero_layer": false
    },
    {
      "layer_idx": 2,
      "total": {
        "original": 218112000,
        "pruned": 217694208,
        "reduced": 417792,
        "reduction_ratio": 0.0019154929577464789
      },
      "attention": {
        "original": 41943040,
        "pruned": 41943040,
        "reduced": 0,
        "reduction_ratio": 0.0
      },
      "mlp": {
        "original": 176160768,
        "pruned": 175742976,
        "reduced": 417792,
        "reduction_ratio": 0.0023716517857142855,
        "intermediate_size": {
          "original": 14336,
          "pruned": 14302
        }
      },
      "is_zero_layer": false
    },
    {
      "layer_idx": 3,
      "total": {
        "original": 218112000,
        "pruned": 214720512,
        "reduced": 3391488,
        "reduction_ratio": 0.015549295774647887
      },
      "attention": {
        "original": 41943040,
        "pruned": 41943040,
        "reduced": 0,
        "reduction_ratio": 0.0
      },
      "mlp": {
        "original": 176160768,
        "pruned": 172769280,
        "reduced": 3391488,
        "reduction_ratio": 0.019252232142857144,
        "intermediate_size": {
          "original": 14336,
          "pruned": 14060
        }
      },
      "is_zero_layer": false
    },
    {
      "layer_idx": 4,
      "total": {
        "original": 218112000,
        "pruned": 211107840,
        "reduced": 7004160,
        "reduction_ratio": 0.03211267605633803
      },
      "attention": {
        "original": 41943040,
        "pruned": 41943040,
        "reduced": 0,
        "reduction_ratio": 0.0
      },
      "mlp": {
        "original": 176160768,
        "pruned": 169156608,
        "reduced": 7004160,
        "reduction_ratio": 0.039760044642857144,
        "intermediate_size": {
          "original": 14336,
          "pruned": 13766
        }
      },
      "is_zero_layer": false
    },
    {
      "layer_idx": 5,
      "total": {
        "original": 218112000,
        "pruned": 204988416,
        "reduced": 13123584,
        "reduction_ratio": 0.06016901408450704
      },
      "attention": {
        "original": 41943040,
        "pruned": 41943040,
        "reduced": 0,
        "reduction_ratio": 0.0
      },
      "mlp": {
        "original": 176160768,
        "pruned": 163037184,
        "reduced": 13123584,
        "reduction_ratio": 0.07449776785714286,
        "intermediate_size": {
          "original": 14336,
          "pruned": 13268
        }
      },
      "is_zero_layer": false
    },
    {
      "layer_idx": 6,
      "total": {
        "original": 218112000,
        "pruned": 196841472,
        "reduced": 21270528,
        "reduction_ratio": 0.09752112676056338
      },
      "attention": {
        "original": 41943040,
        "pruned": 41943040,
        "reduced": 0,
        "reduction_ratio": 0.0
      },
      "mlp": {
        "original": 176160768,
        "pruned": 154890240,
        "reduced": 21270528,
        "reduction_ratio": 0.12074497767857142,
        "intermediate_size": {
          "original": 14336,
          "pruned": 12605
        }
      },
      "is_zero_layer": false
    },
    {
      "layer_idx": 7,
      "total": {
        "original": 218112000,
        "pruned": 186568704,
        "reduced": 31543296,
        "reduction_ratio": 0.14461971830985915
      },
      "attention": {
        "original": 41943040,
        "pruned": 41943040,
        "reduced": 0,
        "reduction_ratio": 0.0
      },
      "mlp": {
        "original": 176160768,
        "pruned": 144617472,
        "reduced": 31543296,
        "reduction_ratio": 0.17905970982142858,
        "intermediate_size": {
          "original": 14336,
          "pruned": 11769
        }
      },
      "is_zero_layer": false
    },
    {
      "layer_idx": 8,
      "total": {
        "original": 218112000,
        "pruned": 180989952,
        "reduced": 37122048,
        "reduction_ratio": 0.17019718309859155
      },
      "attention": {
        "original": 41943040,
        "pruned": 41943040,
        "reduced": 0,
        "reduction_ratio": 0.0
      },
      "mlp": {
        "original": 176160768,
        "pruned": 139038720,
        "reduced": 37122048,
        "reduction_ratio": 0.21072823660714285,
        "intermediate_size": {
          "original": 14336,
          "pruned": 11315
        }
      },
      "is_zero_layer": false
    },
    {
      "layer_idx": 9,
      "total": {
        "original": 218112000,
        "pruned": 179884032,
        "reduced": 38227968,
        "reduction_ratio": 0.1752676056338028
      },
      "attention": {
        "original": 41943040,
        "pruned": 41943040,
        "reduced": 0,
        "reduction_ratio": 0.0
      },
      "mlp": {
        "original": 176160768,
        "pruned": 137932800,
        "reduced": 38227968,
        "reduction_ratio": 0.21700613839285715,
        "intermediate_size": {
          "original": 14336,
          "pruned": 11225
        }
      },
      "is_zero_layer": false
    },
    {
      "layer_idx": 10,
      "total": {
        "original": 218112000,
        "pruned": 173715456,
        "reduced": 44396544,
        "reduction_ratio": 0.2035492957746479
      },
      "attention": {
        "original": 41943040,
        "pruned": 41943040,
        "reduced": 0,
        "reduction_ratio": 0.0
      },
      "mlp": {
        "original": 176160768,
        "pruned": 131764224,
        "reduced": 44396544,
        "reduction_ratio": 0.2520228794642857,
        "intermediate_size": {
          "original": 14336,
          "pruned": 10723
        }
      },
      "is_zero_layer": false
    },
    {
      "layer_idx": 11,
      "total": {
        "original": 218112000,
        "pruned": 171626496,
        "reduced": 46485504,
        "reduction_ratio": 0.21312676056338029
      },
      "attention": {
        "original": 41943040,
        "pruned": 41943040,
        "reduced": 0,
        "reduction_ratio": 0.0
      },
      "mlp": {
        "original": 176160768,
        "pruned": 129675264,
        "reduced": 46485504,
        "reduction_ratio": 0.26388113839285715,
        "intermediate_size": {
          "original": 14336,
          "pruned": 10553
        }
      },
      "is_zero_layer": false
    },
    {
      "layer_idx": 12,
      "total": {
        "original": 218112000,
        "pruned": 164585472,
        "reduced": 53526528,
        "reduction_ratio": 0.24540845070422534
      },
      "attention": {
        "original": 41943040,
        "pruned": 41943040,
        "reduced": 0,
        "reduction_ratio": 0.0
      },
      "mlp": {
        "original": 176160768,
        "pruned": 122634240,
        "reduced": 53526528,
        "reduction_ratio": 0.30385044642857145,
        "intermediate_size": {
          "original": 14336,
          "pruned": 9980
        }
      },
      "is_zero_layer": false
    },
    {
      "layer_idx": 13,
      "total": {
        "original": 218112000,
        "pruned": 160075776,
        "reduced": 58036224,
        "reduction_ratio": 0.2660845070422535
      },
      "attention": {
        "original": 41943040,
        "pruned": 41943040,
        "reduced": 0,
        "reduction_ratio": 0.0
      },
      "mlp": {
        "original": 176160768,
        "pruned": 118124544,
        "reduced": 58036224,
        "reduction_ratio": 0.32945033482142855,
        "intermediate_size": {
          "original": 14336,
          "pruned": 9613
        }
      },
      "is_zero_layer": false
    },
    {
      "layer_idx": 14,
      "total": {
        "original": 218112000,
        "pruned": 170250240,
        "reduced": 47861760,
        "reduction_ratio": 0.21943661971830986
      },
      "attention": {
        "original": 41943040,
        "pruned": 41943040,
        "reduced": 0,
        "reduction_ratio": 0.0
      },
      "mlp": {
        "original": 176160768,
        "pruned": 128299008,
        "reduced": 47861760,
        "reduction_ratio": 0.27169363839285715,
        "intermediate_size": {
          "original": 14336,
          "pruned": 10441
        }
      },
      "is_zero_layer": false
    },
    {
      "layer_idx": 15,
      "total": {
        "original": 218112000,
        "pruned": 167485440,
        "reduced": 50626560,
        "reduction_ratio": 0.23211267605633804
      },
      "attention": {
        "original": 41943040,
        "pruned": 41943040,
        "reduced": 0,
        "reduction_ratio": 0.0
      },
      "mlp": {
        "original": 176160768,
        "pruned": 125534208,
        "reduced": 50626560,
        "reduction_ratio": 0.28738839285714285,
        "intermediate_size": {
          "original": 14336,
          "pruned": 10216
        }
      },
      "is_zero_layer": false
    },
    {
      "layer_idx": 16,
      "total": {
        "original": 218112000,
        "pruned": 160653312,
        "reduced": 57458688,
        "reduction_ratio": 0.26343661971830984
      },
      "attention": {
        "original": 41943040,
        "pruned": 41943040,
        "reduced": 0,
        "reduction_ratio": 0.0
      },
      "mlp": {
        "original": 176160768,
        "pruned": 118702080,
        "reduced": 57458688,
        "reduction_ratio": 0.326171875,
        "intermediate_size": {
          "original": 14336,
          "pruned": 9660
        }
      },
      "is_zero_layer": false
    },
    {
      "layer_idx": 17,
      "total": {
        "original": 218112000,
        "pruned": 164511744,
        "reduced": 53600256,
        "reduction_ratio": 0.24574647887323944
      },
      "attention": {
        "original": 41943040,
        "pruned": 41943040,
        "reduced": 0,
        "reduction_ratio": 0.0
      },
      "mlp": {
        "original": 176160768,
        "pruned": 122560512,
        "reduced": 53600256,
        "reduction_ratio": 0.3042689732142857,
        "intermediate_size": {
          "original": 14336,
          "pruned": 9974
        }
      },
      "is_zero_layer": false
    },
    {
      "layer_idx": 18,
      "total": {
        "original": 218112000,
        "pruned": 152059904,
        "reduced": 66052096,
        "reduction_ratio": 0.30283568075117373
      },
      "attention": {
        "original": 41943040,
        "pruned": 31457280,
        "reduced": 10485760,
        "reduction_ratio": 0.25
      },
      "mlp": {
        "original": 176160768,
        "pruned": 120594432,
        "reduced": 55566336,
        "reduction_ratio": 0.3154296875,
        "intermediate_size": {
          "original": 14336,
          "pruned": 9814
        }
      },
      "is_zero_layer": false
    },
    {
      "layer_idx": 19,
      "total": {
        "original": 218112000,
        "pruned": 149434368,
        "reduced": 68677632,
        "reduction_ratio": 0.3148732394366197
      },
      "attention": {
        "original": 41943040,
        "pruned": 26214400,
        "reduced": 15728640,
        "reduction_ratio": 0.375
      },
      "mlp": {
        "original": 176160768,
        "pruned": 123211776,
        "reduced": 52948992,
        "reduction_ratio": 0.30057198660714285,
        "intermediate_size": {
          "original": 14336,
          "pruned": 10027
        }
      },
      "is_zero_layer": false
    },
    {
      "layer_idx": 20,
      "total": {
        "original": 218112000,
        "pruned": 159727616,
        "reduced": 58384384,
        "reduction_ratio": 0.26768075117370893
      },
      "attention": {
        "original": 41943040,
        "pruned": 31457280,
        "reduced": 10485760,
        "reduction_ratio": 0.25
      },
      "mlp": {
        "original": 176160768,
        "pruned": 128262144,
        "reduced": 47898624,
        "reduction_ratio": 0.2719029017857143,
        "intermediate_size": {
          "original": 14336,
          "pruned": 10438
        }
      },
      "is_zero_layer": false
    },
    {
      "layer_idx": 21,
      "total": {
        "original": 218112000,
        "pruned": 165203968,
        "reduced": 52908032,
        "reduction_ratio": 0.24257276995305163
      },
      "attention": {
        "original": 41943040,
        "pruned": 36700160,
        "reduced": 5242880,
        "reduction_ratio": 0.125
      },
      "mlp": {
        "original": 176160768,
        "pruned": 128495616,
        "reduced": 47665152,
        "reduction_ratio": 0.2705775669642857,
        "intermediate_size": {
          "original": 14336,
          "pruned": 10457
        }
      },
      "is_zero_layer": false
    },
    {
      "layer_idx": 22,
      "total": {
        "original": 218112000,
        "pruned": 166322176,
        "reduced": 51789824,
        "reduction_ratio": 0.23744600938967136
      },
      "attention": {
        "original": 41943040,
        "pruned": 36700160,
        "reduced": 5242880,
        "reduction_ratio": 0.125
      },
      "mlp": {
        "original": 176160768,
        "pruned": 129613824,
        "reduced": 46546944,
        "reduction_ratio": 0.2642299107142857,
        "intermediate_size": {
          "original": 14336,
          "pruned": 10548
        }
      },
      "is_zero_layer": false
    },
    {
      "layer_idx": 23,
      "total": {
        "original": 218112000,
        "pruned": 133398528,
        "reduced": 84713472,
        "reduction_ratio": 0.3883943661971831
      },
      "attention": {
        "original": 41943040,
        "pruned": 10485760,
        "reduced": 31457280,
        "reduction_ratio": 0.75
      },
      "mlp": {
        "original": 176160768,
        "pruned": 122904576,
        "reduced": 53256192,
        "reduction_ratio": 0.3023158482142857,
        "intermediate_size": {
          "original": 14336,
          "pruned": 10002
        }
      },
      "is_zero_layer": false
    },
    {
      "layer_idx": 24,
      "total": {
        "original": 218112000,
        "pruned": 148353024,
        "reduced": 69758976,
        "reduction_ratio": 0.31983098591549297
      },
      "attention": {
        "original": 41943040,
        "pruned": 26214400,
        "reduced": 15728640,
        "reduction_ratio": 0.375
      },
      "mlp": {
        "original": 176160768,
        "pruned": 122130432,
        "reduced": 54030336,
        "reduction_ratio": 0.3067103794642857,
        "intermediate_size": {
          "original": 14336,
          "pruned": 9939
        }
      },
      "is_zero_layer": false
    },
    {
      "layer_idx": 25,
      "total": {
        "original": 218112000,
        "pruned": 145743872,
        "reduced": 72368128,
        "reduction_ratio": 0.33179342723004696
      },
      "attention": {
        "original": 41943040,
        "pruned": 31457280,
        "reduced": 10485760,
        "reduction_ratio": 0.25
      },
      "mlp": {
        "original": 176160768,
        "pruned": 114278400,
        "reduced": 61882368,
        "reduction_ratio": 0.35128348214285715,
        "intermediate_size": {
          "original": 14336,
          "pruned": 9300
        }
      },
      "is_zero_layer": false
    },
    {
      "layer_idx": 26,
      "total": {
        "original": 218112000,
        "pruned": 140324864,
        "reduced": 77787136,
        "reduction_ratio": 0.35663849765258215
      },
      "attention": {
        "original": 41943040,
        "pruned": 31457280,
        "reduced": 10485760,
        "reduction_ratio": 0.25
      },
      "mlp": {
        "original": 176160768,
        "pruned": 108859392,
        "reduced": 67301376,
        "reduction_ratio": 0.38204520089285715,
        "intermediate_size": {
          "original": 14336,
          "pruned": 8859
        }
      },
      "is_zero_layer": false
    },
    {
      "layer_idx": 27,
      "total": {
        "original": 218112000,
        "pruned": 128053248,
        "reduced": 90058752,
        "reduction_ratio": 0.4129014084507042
      },
      "attention": {
        "original": 41943040,
        "pruned": 26214400,
        "reduced": 15728640,
        "reduction_ratio": 0.375
      },
      "mlp": {
        "original": 176160768,
        "pruned": 101830656,
        "reduced": 74330112,
        "reduction_ratio": 0.4219447544642857,
        "intermediate_size": {
          "original": 14336,
          "pruned": 8287
        }
      },
      "is_zero_layer": false
    },
    {
      "layer_idx": 28,
      "total": {
        "original": 218112000,
        "pruned": 123396096,
        "reduced": 94715904,
        "reduction_ratio": 0.4342535211267606
      },
      "attention": {
        "original": 41943040,
        "pruned": 26214400,
        "reduced": 15728640,
        "reduction_ratio": 0.375
      },
      "mlp": {
        "original": 176160768,
        "pruned": 97173504,
        "reduced": 78987264,
        "reduction_ratio": 0.44838169642857145,
        "intermediate_size": {
          "original": 14336,
          "pruned": 7908
        }
      },
      "is_zero_layer": false
    },
    {
      "layer_idx": 29,
      "total": {
        "original": 218112000,
        "pruned": 115126272,
        "reduced": 102985728,
        "reduction_ratio": 0.47216901408450707
      },
      "attention": {
        "original": 41943040,
        "pruned": 26214400,
        "reduced": 15728640,
        "reduction_ratio": 0.375
      },
      "mlp": {
        "original": 176160768,
        "pruned": 88903680,
        "reduced": 87257088,
        "reduction_ratio": 0.49532645089285715,
        "intermediate_size": {
          "original": 14336,
          "pruned": 7235
        }
      },
      "is_zero_layer": false
    },
    {
      "layer_idx": 30,
      "total": {
        "original": 218112000,
        "pruned": 134590464,
        "reduced": 83521536,
        "reduction_ratio": 0.38292957746478873
      },
      "attention": {
        "original": 41943040,
        "pruned": 41943040,
        "reduced": 0,
        "reduction_ratio": 0.0
      },
      "mlp": {
        "original": 176160768,
        "pruned": 92639232,
        "reduced": 83521536,
        "reduction_ratio": 0.47412109375,
        "intermediate_size": {
          "original": 14336,
          "pruned": 7539
        }
      },
      "is_zero_layer": false
    },
    {
      "layer_idx": 31,
      "total": {
        "original": 218112000,
        "pruned": 149970944,
        "reduced": 68141056,
        "reduction_ratio": 0.3124131455399061
      },
      "attention": {
        "original": 41943040,
        "pruned": 31457280,
        "reduced": 10485760,
        "reduction_ratio": 0.25
      },
      "mlp": {
        "original": 176160768,
        "pruned": 118505472,
        "reduced": 57655296,
        "reduction_ratio": 0.32728794642857145,
        "intermediate_size": {
          "original": 14336,
          "pruned": 9644
        }
      },
      "is_zero_layer": false
    }
  ]
}