{
  "extreme_pruning_layers": [
    {
      "layer_idx": 29,
      "pruning_rate": 0.541015625,
      "importance": 4.567763796874455,
      "gradient_mean": 0.05246324464678764,
      "gradient_norm": 357.08369700113934
    },
    {
      "layer_idx": 30,
      "pruning_rate": 0.5889369419642857,
      "importance": 4.145091703959873,
      "gradient_mean": 0.06099161422914929,
      "gradient_norm": 339.7225462595622
    },
    {
      "layer_idx": 31,
      "pruning_rate": 0.5114397321428571,
      "importance": 3.6792133152484894,
      "gradient_mean": 0.0728251217967934,
      "gradient_norm": 313.2208014594184
    }
  ],
  "num_extreme_layers": 3,
  "gradient_statistics": {
    "mean_range": [
      0.04238708513892359,
      0.45077318729211885
    ],
    "mean_ratio": 10.634682350797238,
    "norm_range": [
      248.93723742167154,
      2913.2914318508574
    ],
    "norm_ratio": 11.70291540961749
  },
  "diagnosis": []
}