{
  "model_name": "剪枝后模型",
  "total_params": 6424219648,
  "embedding_params": 525336576,
  "lm_head_params": 525336576,
  "layers": [
    {
      "layer_idx": 0,
      "total": 218112000,
      "attention": {
        "type": "LlamaAttention",
        "q_proj": 16777216,
        "k_proj": 4194304,
        "v_proj": 4194304,
        "o_proj": 16777216,
        "total": 41943040
      },
      "mlp": {
        "type": "LlamaMLP",
        "gate_proj": 58720256,
        "up_proj": 58720256,
        "down_proj": 58720256,
        "total": 176160768,
        "intermediate_size": 14336
      },
      "norm": 8192,
      "is_zero_layer": false
    },
    {
      "layer_idx": 1,
      "total": 218112000,
      "attention": {
        "type": "LlamaAttention",
        "q_proj": 16777216,
        "k_proj": 4194304,
        "v_proj": 4194304,
        "o_proj": 16777216,
        "total": 41943040
      },
      "mlp": {
        "type": "LlamaMLP",
        "gate_proj": 58720256,
        "up_proj": 58720256,
        "down_proj": 58720256,
        "total": 176160768,
        "intermediate_size": 14336
      },
      "norm": 8192,
      "is_zero_layer": false
    },
    {
      "layer_idx": 2,
      "total": 218112000,
      "attention": {
        "type": "LlamaAttention",
        "q_proj": 16777216,
        "k_proj": 4194304,
        "v_proj": 4194304,
        "o_proj": 16777216,
        "total": 41943040
      },
      "mlp": {
        "type": "LlamaMLP",
        "gate_proj": 58720256,
        "up_proj": 58720256,
        "down_proj": 58720256,
        "total": 176160768,
        "intermediate_size": 14336
      },
      "norm": 8192,
      "is_zero_layer": false
    },
    {
      "layer_idx": 3,
      "total": 217571328,
      "attention": {
        "type": "LlamaAttention",
        "q_proj": 16777216,
        "k_proj": 4194304,
        "v_proj": 4194304,
        "o_proj": 16777216,
        "total": 41943040
      },
      "mlp": {
        "type": "LlamaMLP",
        "gate_proj": 58540032,
        "up_proj": 58540032,
        "down_proj": 58540032,
        "total": 175620096,
        "intermediate_size": 14292
      },
      "norm": 8192,
      "is_zero_layer": false
    },
    {
      "layer_idx": 4,
      "total": 217300992,
      "attention": {
        "type": "LlamaAttention",
        "q_proj": 16777216,
        "k_proj": 4194304,
        "v_proj": 4194304,
        "o_proj": 16777216,
        "total": 41943040
      },
      "mlp": {
        "type": "LlamaMLP",
        "gate_proj": 58449920,
        "up_proj": 58449920,
        "down_proj": 58449920,
        "total": 175349760,
        "intermediate_size": 14270
      },
      "norm": 8192,
      "is_zero_layer": false
    },
    {
      "layer_idx": 5,
      "total": 214339584,
      "attention": {
        "type": "LlamaAttention",
        "q_proj": 16777216,
        "k_proj": 4194304,
        "v_proj": 4194304,
        "o_proj": 16777216,
        "total": 41943040
      },
      "mlp": {
        "type": "LlamaMLP",
        "gate_proj": 57462784,
        "up_proj": 57462784,
        "down_proj": 57462784,
        "total": 172388352,
        "intermediate_size": 14029
      },
      "norm": 8192,
      "is_zero_layer": false
    },
    {
      "layer_idx": 6,
      "total": 174120960,
      "attention": {
        "type": "LlamaAttention",
        "q_proj": 16777216,
        "k_proj": 4194304,
        "v_proj": 4194304,
        "o_proj": 16777216,
        "total": 41943040
      },
      "mlp": {
        "type": "LlamaMLP",
        "gate_proj": 44056576,
        "up_proj": 44056576,
        "down_proj": 44056576,
        "total": 132169728,
        "intermediate_size": 10756
      },
      "norm": 8192,
      "is_zero_layer": false
    },
    {
      "layer_idx": 7,
      "total": 150355968,
      "attention": {
        "type": "LlamaAttention",
        "q_proj": 16777216,
        "k_proj": 4194304,
        "v_proj": 4194304,
        "o_proj": 16777216,
        "total": 41943040
      },
      "mlp": {
        "type": "LlamaMLP",
        "gate_proj": 36134912,
        "up_proj": 36134912,
        "down_proj": 36134912,
        "total": 108404736,
        "intermediate_size": 8822
      },
      "norm": 8192,
      "is_zero_layer": false
    },
    {
      "layer_idx": 8,
      "total": 99692544,
      "attention": {
        "type": "LlamaAttention",
        "q_proj": 16777216,
        "k_proj": 4194304,
        "v_proj": 4194304,
        "o_proj": 16777216,
        "total": 41943040
      },
      "mlp": {
        "type": "LlamaMLP",
        "gate_proj": 19247104,
        "up_proj": 19247104,
        "down_proj": 19247104,
        "total": 57741312,
        "intermediate_size": 4699
      },
      "norm": 8192,
      "is_zero_layer": false
    },
    {
      "layer_idx": 9,
      "total": 85757952,
      "attention": {
        "type": "LlamaAttention",
        "q_proj": 16777216,
        "k_proj": 4194304,
        "v_proj": 4194304,
        "o_proj": 16777216,
        "total": 41943040
      },
      "mlp": {
        "type": "LlamaMLP",
        "gate_proj": 14602240,
        "up_proj": 14602240,
        "down_proj": 14602240,
        "total": 43806720,
        "intermediate_size": 3565
      },
      "norm": 8192,
      "is_zero_layer": false
    },
    {
      "layer_idx": 10,
      "total": 81199104,
      "attention": {
        "type": "LlamaAttention",
        "q_proj": 16777216,
        "k_proj": 4194304,
        "v_proj": 4194304,
        "o_proj": 16777216,
        "total": 41943040
      },
      "mlp": {
        "type": "LlamaMLP",
        "gate_proj": 13082624,
        "up_proj": 13082624,
        "down_proj": 13082624,
        "total": 39247872,
        "intermediate_size": 3194
      },
      "norm": 8192,
      "is_zero_layer": false
    },
    {
      "layer_idx": 11,
      "total": 94285824,
      "attention": {
        "type": "LlamaAttention",
        "q_proj": 16777216,
        "k_proj": 4194304,
        "v_proj": 4194304,
        "o_proj": 16777216,
        "total": 41943040
      },
      "mlp": {
        "type": "LlamaMLP",
        "gate_proj": 17444864,
        "up_proj": 17444864,
        "down_proj": 17444864,
        "total": 52334592,
        "intermediate_size": 4259
      },
      "norm": 8192,
      "is_zero_layer": false
    },
    {
      "layer_idx": 12,
      "total": 130940928,
      "attention": {
        "type": "LlamaAttention",
        "q_proj": 16777216,
        "k_proj": 4194304,
        "v_proj": 4194304,
        "o_proj": 16777216,
        "total": 41943040
      },
      "mlp": {
        "type": "LlamaMLP",
        "gate_proj": 29663232,
        "up_proj": 29663232,
        "down_proj": 29663232,
        "total": 88989696,
        "intermediate_size": 7242
      },
      "norm": 8192,
      "is_zero_layer": false
    },
    {
      "layer_idx": 13,
      "total": 91447296,
      "attention": {
        "type": "LlamaAttention",
        "q_proj": 16777216,
        "k_proj": 4194304,
        "v_proj": 4194304,
        "o_proj": 16777216,
        "total": 41943040
      },
      "mlp": {
        "type": "LlamaMLP",
        "gate_proj": 16498688,
        "up_proj": 16498688,
        "down_proj": 16498688,
        "total": 49496064,
        "intermediate_size": 4028
      },
      "norm": 8192,
      "is_zero_layer": false
    },
    {
      "layer_idx": 14,
      "total": 135155712,
      "attention": {
        "type": "LlamaAttention",
        "q_proj": 16777216,
        "k_proj": 4194304,
        "v_proj": 4194304,
        "o_proj": 16777216,
        "total": 41943040
      },
      "mlp": {
        "type": "LlamaMLP",
        "gate_proj": 31068160,
        "up_proj": 31068160,
        "down_proj": 31068160,
        "total": 93204480,
        "intermediate_size": 7585
      },
      "norm": 8192,
      "is_zero_layer": false
    },
    {
      "layer_idx": 15,
      "total": 161624064,
      "attention": {
        "type": "LlamaAttention",
        "q_proj": 16777216,
        "k_proj": 4194304,
        "v_proj": 4194304,
        "o_proj": 16777216,
        "total": 41943040
      },
      "mlp": {
        "type": "LlamaMLP",
        "gate_proj": 39890944,
        "up_proj": 39890944,
        "down_proj": 39890944,
        "total": 119672832,
        "intermediate_size": 9739
      },
      "norm": 8192,
      "is_zero_layer": false
    },
    {
      "layer_idx": 16,
      "total": 193880064,
      "attention": {
        "type": "LlamaAttention",
        "q_proj": 16777216,
        "k_proj": 4194304,
        "v_proj": 4194304,
        "o_proj": 16777216,
        "total": 41943040
      },
      "mlp": {
        "type": "LlamaMLP",
        "gate_proj": 50642944,
        "up_proj": 50642944,
        "down_proj": 50642944,
        "total": 151928832,
        "intermediate_size": 12364
      },
      "norm": 8192,
      "is_zero_layer": false
    },
    {
      "layer_idx": 17,
      "total": 205160448,
      "attention": {
        "type": "LlamaAttention",
        "q_proj": 16777216,
        "k_proj": 4194304,
        "v_proj": 4194304,
        "o_proj": 16777216,
        "total": 41943040
      },
      "mlp": {
        "type": "LlamaMLP",
        "gate_proj": 54403072,
        "up_proj": 54403072,
        "down_proj": 54403072,
        "total": 163209216,
        "intermediate_size": 13282
      },
      "norm": 8192,
      "is_zero_layer": false
    },
    {
      "layer_idx": 18,
      "total": 197627904,
      "attention": {
        "type": "LlamaAttention",
        "q_proj": 16777216,
        "k_proj": 4194304,
        "v_proj": 4194304,
        "o_proj": 16777216,
        "total": 41943040
      },
      "mlp": {
        "type": "LlamaMLP",
        "gate_proj": 51892224,
        "up_proj": 51892224,
        "down_proj": 51892224,
        "total": 155676672,
        "intermediate_size": 12669
      },
      "norm": 8192,
      "is_zero_layer": false
    },
    {
      "layer_idx": 19,
      "total": 159817728,
      "attention": {
        "type": "LlamaAttention",
        "q_proj": 16777216,
        "k_proj": 4194304,
        "v_proj": 4194304,
        "o_proj": 16777216,
        "total": 41943040
      },
      "mlp": {
        "type": "LlamaMLP",
        "gate_proj": 39288832,
        "up_proj": 39288832,
        "down_proj": 39288832,
        "total": 117866496,
        "intermediate_size": 9592
      },
      "norm": 8192,
      "is_zero_layer": false
    },
    {
      "layer_idx": 20,
      "total": 163491840,
      "attention": {
        "type": "LlamaAttention",
        "q_proj": 16777216,
        "k_proj": 4194304,
        "v_proj": 4194304,
        "o_proj": 16777216,
        "total": 41943040
      },
      "mlp": {
        "type": "LlamaMLP",
        "gate_proj": 40513536,
        "up_proj": 40513536,
        "down_proj": 40513536,
        "total": 121540608,
        "intermediate_size": 9891
      },
      "norm": 8192,
      "is_zero_layer": false
    },
    {
      "layer_idx": 21,
      "total": 192466944,
      "attention": {
        "type": "LlamaAttention",
        "q_proj": 16777216,
        "k_proj": 4194304,
        "v_proj": 4194304,
        "o_proj": 16777216,
        "total": 41943040
      },
      "mlp": {
        "type": "LlamaMLP",
        "gate_proj": 50171904,
        "up_proj": 50171904,
        "down_proj": 50171904,
        "total": 150515712,
        "intermediate_size": 12249
      },
      "norm": 8192,
      "is_zero_layer": false
    },
    {
      "layer_idx": 22,
      "total": 182120448,
      "attention": {
        "type": "LlamaAttention",
        "q_proj": 16777216,
        "k_proj": 4194304,
        "v_proj": 4194304,
        "o_proj": 16777216,
        "total": 41943040
      },
      "mlp": {
        "type": "LlamaMLP",
        "gate_proj": 46723072,
        "up_proj": 46723072,
        "down_proj": 46723072,
        "total": 140169216,
        "intermediate_size": 11407
      },
      "norm": 8192,
      "is_zero_layer": false
    },
    {
      "layer_idx": 23,
      "total": 176271360,
      "attention": {
        "type": "LlamaAttention",
        "q_proj": 16777216,
        "k_proj": 4194304,
        "v_proj": 4194304,
        "o_proj": 16777216,
        "total": 41943040
      },
      "mlp": {
        "type": "LlamaMLP",
        "gate_proj": 44773376,
        "up_proj": 44773376,
        "down_proj": 44773376,
        "total": 134320128,
        "intermediate_size": 10931
      },
      "norm": 8192,
      "is_zero_layer": false
    },
    {
      "layer_idx": 24,
      "total": 156119040,
      "attention": {
        "type": "LlamaAttention",
        "q_proj": 16777216,
        "k_proj": 4194304,
        "v_proj": 4194304,
        "o_proj": 16777216,
        "total": 41943040
      },
      "mlp": {
        "type": "LlamaMLP",
        "gate_proj": 38055936,
        "up_proj": 38055936,
        "down_proj": 38055936,
        "total": 114167808,
        "intermediate_size": 9291
      },
      "norm": 8192,
      "is_zero_layer": false
    },
    {
      "layer_idx": 25,
      "total": 146620416,
      "attention": {
        "type": "LlamaAttention",
        "q_proj": 16777216,
        "k_proj": 4194304,
        "v_proj": 4194304,
        "o_proj": 16777216,
        "total": 41943040
      },
      "mlp": {
        "type": "LlamaMLP",
        "gate_proj": 34889728,
        "up_proj": 34889728,
        "down_proj": 34889728,
        "total": 104669184,
        "intermediate_size": 8518
      },
      "norm": 8192,
      "is_zero_layer": false
    },
    {
      "layer_idx": 26,
      "total": 152420352,
      "attention": {
        "type": "LlamaAttention",
        "q_proj": 16777216,
        "k_proj": 4194304,
        "v_proj": 4194304,
        "o_proj": 16777216,
        "total": 41943040
      },
      "mlp": {
        "type": "LlamaMLP",
        "gate_proj": 36823040,
        "up_proj": 36823040,
        "down_proj": 36823040,
        "total": 110469120,
        "intermediate_size": 8990
      },
      "norm": 8192,
      "is_zero_layer": false
    },
    {
      "layer_idx": 27,
      "total": 177770496,
      "attention": {
        "type": "LlamaAttention",
        "q_proj": 16777216,
        "k_proj": 4194304,
        "v_proj": 4194304,
        "o_proj": 16777216,
        "total": 41943040
      },
      "mlp": {
        "type": "LlamaMLP",
        "gate_proj": 45273088,
        "up_proj": 45273088,
        "down_proj": 45273088,
        "total": 135819264,
        "intermediate_size": 11053
      },
      "norm": 8192,
      "is_zero_layer": false
    },
    {
      "layer_idx": 28,
      "total": 117190656,
      "attention": {
        "type": "LlamaAttention",
        "q_proj": 16777216,
        "k_proj": 4194304,
        "v_proj": 4194304,
        "o_proj": 16777216,
        "total": 41943040
      },
      "mlp": {
        "type": "LlamaMLP",
        "gate_proj": 25079808,
        "up_proj": 25079808,
        "down_proj": 25079808,
        "total": 75239424,
        "intermediate_size": 6123
      },
      "norm": 8192,
      "is_zero_layer": false
    },
    {
      "layer_idx": 29,
      "total": 209055744,
      "attention": {
        "type": "LlamaAttention",
        "q_proj": 16777216,
        "k_proj": 4194304,
        "v_proj": 4194304,
        "o_proj": 16777216,
        "total": 41943040
      },
      "mlp": {
        "type": "LlamaMLP",
        "gate_proj": 55701504,
        "up_proj": 55701504,
        "down_proj": 55701504,
        "total": 167104512,
        "intermediate_size": 13599
      },
      "norm": 8192,
      "is_zero_layer": false
    },
    {
      "layer_idx": 30,
      "total": 217288704,
      "attention": {
        "type": "LlamaAttention",
        "q_proj": 16777216,
        "k_proj": 4194304,
        "v_proj": 4194304,
        "o_proj": 16777216,
        "total": 41943040
      },
      "mlp": {
        "type": "LlamaMLP",
        "gate_proj": 58445824,
        "up_proj": 58445824,
        "down_proj": 58445824,
        "total": 175337472,
        "intermediate_size": 14269
      },
      "norm": 8192,
      "is_zero_layer": false
    },
    {
      "layer_idx": 31,
      "total": 218112000,
      "attention": {
        "type": "LlamaAttention",
        "q_proj": 16777216,
        "k_proj": 4194304,
        "v_proj": 4194304,
        "o_proj": 16777216,
        "total": 41943040
      },
      "mlp": {
        "type": "LlamaMLP",
        "gate_proj": 58720256,
        "up_proj": 58720256,
        "down_proj": 58720256,
        "total": 176160768,
        "intermediate_size": 14336
      },
      "norm": 8192,
      "is_zero_layer": false
    }
  ],
  "layer_summary": {
    "num_layers": 32,
    "total_layer_params": 5373542400
  }
}